dcegm/__init__.py
dcegm/_version.py
dcegm/asset_correction.py
dcegm/backward_induction.py
dcegm/check_func_outputs.py
dcegm/cli.py
dcegm/final_periods.py
dcegm/law_of_motion.py
dcegm/likelihood.py
dcegm/numerical_integration.py
dcegm/solve_single_period.py
dcegm/egm/__init__.py
dcegm/egm/aggregate_marginal_utility.py
dcegm/egm/interpolate_marginal_utility.py
dcegm/egm/solve_euler_equation.py
dcegm/interfaces/__init__.py
dcegm/interfaces/inspect_structure.py
dcegm/interfaces/interface.py
dcegm/interfaces/model_class.py
dcegm/interfaces/sol_interface.py
dcegm/interpolation/__init__.py
dcegm/interpolation/interp1d.py
dcegm/interpolation/interp2d.py
dcegm/pre_processing/__init__.py
dcegm/pre_processing/alternative_sim_functions.py
dcegm/pre_processing/check_model_config.py
dcegm/pre_processing/check_model_specs.py
dcegm/pre_processing/check_params.py
dcegm/pre_processing/setup_model.py
dcegm/pre_processing/shared.py
dcegm/pre_processing/batches/__init__.py
dcegm/pre_processing/batches/algo_batch_size.py
dcegm/pre_processing/batches/batch_creation.py
dcegm/pre_processing/batches/last_two_periods.py
dcegm/pre_processing/batches/single_segment.py
dcegm/pre_processing/model_functions/__init__.py
dcegm/pre_processing/model_functions/process_model_functions.py
dcegm/pre_processing/model_functions/taste_shock_function.py
dcegm/pre_processing/model_functions/upper_evelope_wrapper.py
dcegm/pre_processing/model_structure/__init__.py
dcegm/pre_processing/model_structure/deterministic_states.py
dcegm/pre_processing/model_structure/model_structure.py
dcegm/pre_processing/model_structure/shared.py
dcegm/pre_processing/model_structure/state_choice_space.py
dcegm/pre_processing/model_structure/state_space.py
dcegm/pre_processing/model_structure/stochastic_states.py
dcegm/simulation/__init__.py
dcegm/simulation/random_keys.py
dcegm/simulation/sim_utils.py
dcegm/simulation/simulate.py
dcegm/simulation/taste_shocks.py
dcegm/templates/fullmodel/run_example.ipynb
dcegm-0.1.0.dev0.dist-info/METADATA
dcegm-0.1.0.dev0.dist-info/WHEEL
dcegm-0.1.0.dev0.dist-info/licenses/LICENSE
dcegm-0.1.0.dev0.dist-info/RECORD
