Metadata-Version: 2.4
Name: dcegm
Version: 0.1.0.dev0
Summary: Python package for solving and simulating finite-horizon stochastic discrete-continuous dynamic choice models using the DC-EGM algorithm from Iskhakov, Jørgensen, Rust, and Schjerning (QE, 2017).
Project-URL: Github, https://github.com/OpenSourceEconomics/dcegm
Author-email: "Max Blesch, Sebastian Gsell" <gsell.sebastian@gmail.com>
Maintainer-email: "Max Blesch, Sebastian Gsell" <maximilian.blesch@hu-berlin.de>
License: MIT
License-File: LICENSE
Keywords: Computational Economics,DC-EGM,Dynamic Programming,Econometrics,Economics,Life Cycle Models,Statistics
Classifier: Development Status :: 3 - Alpha
Classifier: Intended Audience :: Science/Research
Classifier: License :: OSI Approved :: MIT License
Classifier: Operating System :: MacOS :: MacOS X
Classifier: Operating System :: Microsoft :: Windows
Classifier: Operating System :: POSIX
Classifier: Programming Language :: Python :: 3.10
Classifier: Programming Language :: Python :: 3.11
Classifier: Programming Language :: Python :: 3.12
Classifier: Programming Language :: Python :: 3.13
Classifier: Topic :: Scientific/Engineering
Requires-Python: >=3.10
Requires-Dist: jax
Requires-Dist: numpy
